[{"hotel_name": "Candlewood Suites Indianapolis Airport", "distance": 6.96, "room_name": "Studio Suite - King Bed", "rate": 165.0, "skywalk": 1, "downtown": 0}, {"hotel_name": "Candlewood Suites Indianapolis Airport", "distance": 6.96, "room_name": "One Bedroom Suite - Queen Bed w&#x2f;Pullout", "rate": 185.0, "skywalk": 1, "downtown": 0}, {"hotel_name": "Candlewood Suites Indianapolis Airport", "distance": 6.96, "room_name": "Studio Suite - Queen&#x2f;Queen", "rate": 185.0, "skywalk": 1, "downtown": 0}, {"hotel_name": "Hyatt Place - Indianapolis Airport", "distance": 7.07, "room_name": "King Suite with Pull Sofa", "rate": 181.0, "skywalk": 0, "downtown": 0}, {"hotel_name": "Hyatt Place - Indianapolis Airport", "distance": 7.07, "room_name": "Double&#x2f;Double Suite", "rate": 191.0, "skywalk": 0, "downtown": 0}, {"hotel_name": "Courtyard Indianapolis Airport", "distance": 7.18, "room_name": "Standard King &#x2b; Pullout Sofa", "rate": 202.0, "skywalk": 0, "downtown": 0}, {"hotel_name": "Courtyard Indianapolis Airport", "distance": 7.18, "room_name": "Standard Double&#x2f;Double", "rate": 212.0, "skywalk": 0, "downtown": 0}, {"hotel_name": "Delta Hotels by Marriott Indianapolis Airport", "distance": 7.18, "room_name": "King Room", "rate": 219.0, "skywalk": 0, "downtown": 0}, {"hotel_name": "La Quinta Inn Airport Executive Drive", "distance": 7.33, "room_name": "Standard King Room", "rate": 119.0, "skywalk": 0, "downtown": 0}, {"hotel_name": "La Quinta Inn Airport Executive Drive", "distance": 7.33, "room_name": "Standard Queen&#x2f;Queen Room", "rate": 129.0, "skywalk": 0, "downtown": 0}, {"hotel_name": "Holiday Inn Indianapolis - Airport Area North", "distance": 7.38, "room_name": "Standard King Room", "rate": 180.0, "skywalk": 0, "downtown": 0}, {"hotel_name": "Holiday Inn Indianapolis - Airport Area North", "distance": 7.38, "room_name": "Standard Queen&#x2f;Queen Room", "rate": 189.0, "skywalk": 0, "downtown": 0}, {"hotel_name": "Comfort Inn East Indianapolis", "distance": 8.51, "room_name": "Standard Double&#x2f;Double", "rate": 159.0, "skywalk": 0, "downtown": 0}, {"hotel_name": "Holiday Inn Express South", "distance": 9.14, "room_name": "Standard Double&#x2f;Double", "rate": 145.0, "skywalk": 0, "downtown": 0}, {"hotel_name": "Holiday Inn Express South", "distance": 9.14, "room_name": "Standard King", "rate": 145.0, "skywalk": 0, "downtown": 0}, {"hotel_name": "Baymont Inn &amp; Suites - Indianapolis West", "distance": 9.75, "room_name": "Standard Full&#x2f;Full", "rate": 139.0, "skywalk": 0, "downtown": 0}, {"hotel_name": "Baymont Inn &amp; Suites - Indianapolis West", "distance": 9.75, "room_name": "Standard King", "rate": 139.0, "skywalk": 0, "downtown": 0}, {"hotel_name": "Baymont Inn &amp; Suites Indianapolis Brookville Crossing", "distance": 12.69, "room_name": "Standard Double&#x2f;Double", "rate": 184.0, "skywalk": 0, "downtown": 0}, {"hotel_name": "Clarion Inn &amp; Suites Northwest", "distance": 12.79, "room_name": "1 King Bed w&#x2f;Sleeper Sofa", "rate": 145.0, "skywalk": 0, "downtown": 0}, {"hotel_name": "Clarion Inn &amp; Suites Northwest", "distance": 12.79, "room_name": "2 Queen Beds", "rate": 155.0, "skywalk": 0, "downtown": 0}, {"hotel_name": "Home2 Suites by Hilton Indianapolis Airport", "distance": 13.1, "room_name": "King Studio Suite w&#x2f; Sleeper Sofa", "rate": 168.0, "skywalk": 0, "downtown": 0}, {"hotel_name": "Home2 Suites by Hilton Indianapolis Airport", "distance": 13.1, "room_name": "Queen&#x2f;Queen Studio Suite w&#x2f; Sleeper Sofa", "rate": 172.0, "skywalk": 0, "downtown": 0}, {"hotel_name": "Hilton Garden Inn Indianapolis Airport", "distance": 13.38, "room_name": "King Room", "rate": 168.0, "skywalk": 0, "downtown": 0}, {"hotel_name": "Hilton Garden Inn Indianapolis Airport", "distance": 13.38, "room_name": "Two Queen Beds", "rate": 168.0, "skywalk": 0, "downtown": 0}, {"hotel_name": "Baymont by Wyndham - Airport&#x2f;Plainfield", "distance": 15.1, "room_name": "King w&#x2f; Sofa Sleeper", "rate": 159.0, "skywalk": 0, "downtown": 0}, {"hotel_name": "Courtyard by Marriott Indianapolis Plainfield", "distance": 15.33, "room_name": "2 Queen Beds", "rate": 243.0, "skywalk": 0, "downtown": 0}]